pre_processing_text_basic_tools_br/__init__.py
pre_processing_text_basic_tools_br/main.py
pre_processing_text_basic_tools_br-0.9.4.dist-info/LICENSE
pre_processing_text_basic_tools_br-0.9.4.dist-info/METADATA
pre_processing_text_basic_tools_br-0.9.4.dist-info/WHEEL
pre_processing_text_basic_tools_br-0.9.4.dist-info/top_level.txt
pre_processing_text_basic_tools_br-0.9.4.dist-info/RECORD
