Metadata-Version: 2.1
Name: pre_processing_text_basic_tools_br
Version: 0.9.4
Summary: Kit de ferramentas para processos básicos de Processamento de Linguagem Natural.
Author: Igor Caetano de Souza
Project-URL: GitHub Repository, https://github.com/IgorCaetano/pre_processing_text_basic_tools_br
License-File: LICENSE
Requires-Dist: regex
